moirai_sklearn/__init__.py
moirai_sklearn/forecaster.py
moirai_sklearn-0.1.1.dist-info/licenses/LICENSE
moirai_sklearn-0.1.1.dist-info/METADATA
moirai_sklearn-0.1.1.dist-info/WHEEL
moirai_sklearn-0.1.1.dist-info/top_level.txt
moirai_sklearn-0.1.1.dist-info/RECORD
