Metadata-Version: 2.4
Name: moirai_sklearn
Version: 0.1.1
Summary: A scikit-learn-like interface for Moirai time series forecasting using native quantile outputs
Author-email: Your Name <your.email@example.com>
License: Apache-2.0
Project-URL: Homepage, https://github.com/guyko81/moirai_sklearn
Project-URL: Documentation, https://github.com/guyko81/moirai_sklearn#readme
Project-URL: Repository, https://github.com/guyko81/moirai_sklearn
Keywords: time-series,forecasting,machine-learning,moirai,distribution
Classifier: Development Status :: 3 - Alpha
Classifier: Intended Audience :: Developers
Classifier: Intended Audience :: Science/Research
Classifier: License :: OSI Approved :: Apache Software License
Classifier: Programming Language :: Python :: 3
Classifier: Programming Language :: Python :: 3.10
Classifier: Programming Language :: Python :: 3.11
Classifier: Topic :: Scientific/Engineering :: Artificial Intelligence
Requires-Python: >=3.10
License-File: LICENSE
Requires-Dist: numpy>=1.21
Requires-Dist: pandas>=1.3
Requires-Dist: torch>=2.0
Requires-Dist: uni2ts>=2.0.0
Provides-Extra: dev
Requires-Dist: pytest>=7.0; extra == "dev"
Requires-Dist: pytest-cov>=4.0; extra == "dev"
Dynamic: license-file
